haorm/__init__.py
haorm/context.py
haorm/core.py
haorm/meta_reflex.py
haorm/router.py
haorm/settings.py
haorm-1.0.0.dist-info/AUTHORS
haorm-1.0.0.dist-info/LICENSE
haorm-1.0.0.dist-info/METADATA
haorm-1.0.0.dist-info/WHEEL
haorm-1.0.0.dist-info/entry_points.txt
haorm-1.0.0.dist-info/pbr.json
haorm-1.0.0.dist-info/top_level.txt
haorm-1.0.0.dist-info/RECORD
