Metadata-Version: 2.1
Name: haorm
Version: 1.0.0
Summary: awsome project created by pycman.
Home-page: http://example.com
Author: singein
Author-email: singein@outlook.com
License: MIT
Platform: UNKNOWN
Requires-Python: >= 3.6
License-File: LICENSE
License-File: AUTHORS
Requires-Dist: django
Requires-Dist: mysqlclient
Requires-Dist: loguru
